mexc_api/__init__.py
mexc_api/common/__init__.py
mexc_api/common/api.py
mexc_api/common/enums.py
mexc_api/common/exceptions.py
mexc_api/common/utils.py
mexc_api/spot/__init__.py
mexc_api/spot/endpoints/_account.py
mexc_api/spot/endpoints/_etf.py
mexc_api/spot/endpoints/_market.py
mexc_api/spot/endpoints/_rebate.py
mexc_api/spot/endpoints/_sub_account.py
mexc_api/spot/endpoints/_wallet.py
mexc_api/websocket/__init__.py
mexc_api/websocket/mexc_websocket_app.py
mexc_api/websocket/websocket_stream.py
mexc_api-0.0.2.dist-info/LICENSE
mexc_api-0.0.2.dist-info/METADATA
mexc_api-0.0.2.dist-info/WHEEL
mexc_api-0.0.2.dist-info/top_level.txt
mexc_api-0.0.2.dist-info/RECORD
