Metadata-Version: 2.1
Name: mexc-api
Version: 0.0.2
Summary: A wrapper for the Mexc rest and websocket api.
Author-email: Floris272 <florispuijk@outlook.com>
License: MIT
Project-URL: Homepage, https://github.com/Floris272/py-mexc-api
Project-URL: Bug Tracker, https://github.com/Floris272/py-mexc-api/issues
Classifier: Programming Language :: Python :: 3
Classifier: License :: OSI Approved :: MIT License
Classifier: Operating System :: OS Independent
Requires-Python: >=3.11
License-File: LICENSE
Requires-Dist: requests >=2.31.0
Requires-Dist: websocket-client >=1.6.1
